fireducks/__init__.py
fireducks/_version.py
fireducks/core.py
fireducks/errors/__init__.py
fireducks/fallback.py
fireducks/fireducks_ext.so
fireducks/frovedis_initialize.py
fireducks/imhook.py
fireducks/importhook/__init__.py
fireducks/importhook/__main__.py
fireducks/importhook/_decorator.py
fireducks/importhook/_util.py
fireducks/ipyext.py
fireducks/ir.py
fireducks/irutils.py
fireducks/log.py
fireducks/pandas/__init__.py
fireducks/pandas/__main__.py
fireducks/pandas/aggregate.py
fireducks/pandas/api.py
fireducks/pandas/binop.py
fireducks/pandas/config.py
fireducks/pandas/expr.py
fireducks/pandas/feat.py
fireducks/pandas/frame.py
fireducks/pandas/generic.py
fireducks/pandas/groupby.py
fireducks/pandas/hinting/__init__.py
fireducks/pandas/hinting/hint.py
fireducks/pandas/hinting/ops.py
fireducks/pandas/indexing.py
fireducks/pandas/io/__init__.py
fireducks/pandas/io/api.py
fireducks/pandas/io/parquet.py
fireducks/pandas/metadata.py
fireducks/pandas/rolling.py
fireducks/pandas/series.py
fireducks/pandas/utils.py
fireducks/pandas/wrappers.py
fireducks/testing.py
fireducks/tracing/__init__.py
fireducks/tracing/helper.py
fireducks-1.4.3.dist-info/LICENSES/LICENSE.txt
fireducks-1.4.3.dist-info/LICENSES/NOTICE.txt
fireducks-1.4.3.dist-info/METADATA
fireducks-1.4.3.dist-info/WHEEL
fireducks-1.4.3.dist-info/RECORD
