Metadata-Version: 2.1
Name: fireducks
Version: 1.4.3
Summary: Compiler Accelerated DataFrame
Author: FireDucks Development Team
Author-email: contact@fireducks.jp.nec.com
Requires-Python: >=3.9,<3.14
Classifier: Development Status :: 5 - Production/Stable
Classifier: Environment :: Console
Classifier: Intended Audience :: Science/Research
Classifier: License :: OSI Approved :: BSD License
Classifier: Operating System :: POSIX :: Linux
Classifier: Programming Language :: Python :: 3
Classifier: Programming Language :: Python :: 3.9
Classifier: Programming Language :: Python :: 3.10
Classifier: Programming Language :: Python :: 3.11
Classifier: Programming Language :: Python :: 3.12
Classifier: Programming Language :: Python :: 3.13
Classifier: Topic :: Scientific/Engineering
Requires-Dist: firefw (==1.4.3)
Requires-Dist: pandas (>=1.5.3,<2.4.0)
Requires-Dist: pyarrow (>=21.0,<21.1)
